{"items":[{"user":{"reputation":213085,"user_id":215945,"user_type":"registered","accept_rate":97},"post_count":717,"score":17184},{"user":{"reputation":110962,"user_id":259038,"user_type":"registered"},"post_count":113,"score":12092},{"user":{"reputation":96813,"user_id":1418796,"user_type":"registered"},"post_count":352,"score":9003},{"user":{"reputation":82131,"user_id":135786,"user_type":"registered","accept_rate":97},"post_count":304,"score":6628},{"user":{"reputation":47828,"user_id":1095616,"user_type":"registered"},"post_count":312,"score":4410},{"user":{"reputation":70808,"user_id":2435473,"user_type":"registered","accept_rate":56},"post_count":2511,"score":4235},{"user":{"reputation":41004,"user_id":192810,"user_type":"registered"},"post_count":32,"score":3737},{"user":{"reputation":83511,"user_id":1679310,"user_type":"registered"},"post_count":924,"score":3595},{"user":{"reputation":37290,"user_id":1397051,"user_type":"registered","accept_rate":89},"post_count":135,"score":3547},{"user":{"reputation":32936,"user_id":493075,"user_type":"registered"},"post_count":55,"score":2913},{"user":{"reputation":32110,"user_id":2614013,"user_type":"registered","accept_rate":88},"post_count":258,"score":2901},{"user":{"reputation":126468,"user_id":949476,"user_type":"registered"},"post_count":1316,"score":2822},{"user":{"reputation":94342,"user_id":1009603,"user_type":"registered","accept_rate":60},"post_count":736,"score":2811},{"user":{"reputation":32023,"user_id":1207991,"user_type":"registered","accept_rate":40},"post_count":97,"score":2779},{"user":{"reputation":28386,"user_id":1238847,"user_type":"registered"},"post_count":130,"score":2589},{"user":{"reputation":36010,"user_id":361151,"user_type":"registered","accept_rate":67},"post_count":928,"score":2520},{"user":{"reputation":30160,"user_id":1875004,"user_type":"registered","accept_rate":93},"post_count":77,"score":2473},{"user":{"reputation":27980,"user_id":825780,"user_type":"registered","accept_rate":81},"post_count":92,"score":2436},{"user":{"reputation":29792,"user_id":2887841,"user_type":"registered"},"post_count":387,"score":2412},{"user":{"reputation":102439,"user_id":62082,"user_type":"registered","accept_rate":81},"post_count":142,"score":2368}],"has_more":false,"quota_max":300,"quota_remaining":245}