{"items":[{"user":{"reputation":910370,"user_id":22656,"user_type":"registered","accept_rate":86},"post_count":313,"score":3716},{"user":{"reputation":50682,"user_id":11830,"user_type":"registered"},"post_count":1,"score":3062},{"user":{"reputation":90248,"user_id":1965,"user_type":"registered","accept_rate":50},"post_count":2,"score":2406},{"user":{"reputation":458928,"user_id":23283,"user_type":"registered","accept_rate":100},"post_count":39,"score":1767},{"user":{"reputation":245310,"user_id":9530,"user_type":"registered","accept_rate":78},"post_count":9,"score":1629},{"user":{"reputation":123929,"user_id":13531,"user_type":"moderator","accept_rate":75},"post_count":9,"score":1588},{"user":{"reputation":15753,"user_id":109103,"user_type":"registered"},"post_count":2,"score":1320},{"user":{"reputation":15316,"user_id":446,"user_type":"registered"},"post_count":1,"score":1293},{"user":{"reputation":548540,"user_id":34397,"user_type":"registered","accept_rate":87},"post_count":52,"score":1212},{"user":{"reputation":19797,"user_id":56829,"user_type":"registered","accept_rate":82},"post_count":1,"score":1137},{"user":{"reputation":42257,"user_id":125844,"user_type":"registered","accept_rate":85},"post_count":3,"score":927},{"user":{"reputation":216692,"user_id":276101,"user_type":"registered","accept_rate":67},"post_count":16,"score":905},{"user":{"reputation":23032,"user_id":84378,"user_type":"registered","accept_rate":85},"post_count":3,"score":901},{"user":{"reputation":134917,"user_id":615,"user_type":"registered","accept_rate":95},"post_count":7,"score":751},{"user":{"reputation":67757,"user_id":905,"user_type":"registered","accept_rate":78},"post_count":8,"score":742},{"user":{"reputation":345416,"user_id":34509,"user_type":"registered","accept_rate":63},"post_count":28,"score":723},{"user":{"reputation":187012,"user_id":40342,"user_type":"registered","accept_rate":62},"post_count":31,"score":694},{"user":{"reputation":357483,"user_id":57695,"user_type":"registered","accept_rate":83},"post_count":141,"score":687},{"user":{"reputation":18141,"user_id":2361,"user_type":"registered","accept_rate":85},"post_count":4,"score":676},{"user":{"reputation":10611,"user_id":7418,"user_type":"registered","accept_rate":100},"post_count":3,"score":643}],"has_more":false,"quota_max":10000,"quota_remaining":9533}