{"items":[{"user":{"reputation":637657,"user_id":6309,"user_type":"registered","accept_rate":100},"post_count":2189,"score":9924},{"user":{"reputation":187671,"user_id":223092,"user_type":"registered","accept_rate":68},"post_count":79,"score":5704},{"user":{"reputation":458708,"user_id":23283,"user_type":"registered","accept_rate":100},"post_count":4,"score":2373},{"user":{"reputation":59260,"user_id":1864976,"user_type":"registered","accept_rate":100},"post_count":129,"score":1622},{"user":{"reputation":29813,"user_id":335418,"user_type":"registered","accept_rate":83},"post_count":122,"score":1609},{"user":{"reputation":16207,"user_id":243559,"user_type":"registered"},"post_count":49,"score":1552},{"user":{"reputation":156493,"user_id":526535,"user_type":"registered","accept_rate":85},"post_count":115,"score":1385},{"user":{"reputation":217739,"user_id":28804,"user_type":"registered","accept_rate":76},"post_count":80,"score":1103},{"user":{"reputation":12900,"user_id":720030,"user_type":"registered"},"post_count":1,"score":1085},{"user":{"reputation":232699,"user_id":119963,"user_type":"registered"},"post_count":38,"score":918},{"user":{"reputation":18479,"user_id":17123,"user_type":"registered","accept_rate":67},"post_count":1,"score":873},{"user":{"reputation":60920,"user_id":2119,"user_type":"registered","accept_rate":71},"post_count":1,"score":771},{"user":{"reputation":52665,"user_id":39975,"user_type":"registered","accept_rate":75},"post_count":9,"score":744},{"user":{"reputation":17342,"user_id":159721,"user_type":"registered","accept_rate":82},"post_count":5,"score":713},{"user":{"reputation":17261,"user_id":1454806,"user_type":"registered"},"post_count":2,"score":680},{"user":{"reputation":7928,"user_id":509939,"user_type":"registered"},"post_count":1,"score":602},{"user":{"reputation":11088,"user_id":20045,"user_type":"registered"},"post_count":1,"score":571},{"user":{"reputation":9542,"user_id":489586,"user_type":"registered","accept_rate":74},"post_count":1,"score":568},{"user":{"reputation":6368,"user_id":562154,"user_type":"registered","accept_rate":71},"post_count":1,"score":555},{"user":{"reputation":13342,"user_id":164171,"user_type":"registered","accept_rate":97},"post_count":1,"score":504}],"has_more":false,"quota_max":300,"quota_remaining":34}