{"items":[{"user":{"reputation":72025,"user_id":21926,"user_type":"registered"},"post_count":15,"score":2760},{"user":{"reputation":324016,"user_id":1968,"user_type":"registered","accept_rate":83},"post_count":10,"score":1608},{"user":{"reputation":68661,"user_id":2214,"user_type":"registered","accept_rate":100},"post_count":1,"score":980},{"user":{"reputation":8539,"user_id":1505540,"user_type":"registered"},"post_count":1,"score":827},{"user":{"reputation":7122,"user_id":851045,"user_type":"registered","accept_rate":80},"post_count":1,"score":714},{"user":{"reputation":401489,"user_id":53114,"user_type":"registered","accept_rate":45},"post_count":30,"score":673},{"user":{"reputation":14766,"user_id":264395,"user_type":"registered","accept_rate":90},"post_count":5,"score":550},{"user":{"reputation":910370,"user_id":22656,"user_type":"registered","accept_rate":86},"post_count":45,"score":549},{"user":{"reputation":86205,"user_id":449449,"user_type":"registered","accept_rate":100},"post_count":7,"score":527},{"user":{"reputation":10878,"user_id":1359785,"user_type":"registered","accept_rate":97},"post_count":1,"score":524},{"user":{"reputation":7835,"user_id":74089,"user_type":"registered","accept_rate":97},"post_count":1,"score":516},{"user":{"reputation":17319,"user_id":7469,"user_type":"registered","accept_rate":86},"post_count":3,"score":406},{"user":{"reputation":391699,"user_id":548225,"user_type":"registered","accept_rate":90},"post_count":208,"score":400},{"user":{"reputation":216692,"user_id":276101,"user_type":"registered","accept_rate":67},"post_count":14,"score":398},{"user":{"reputation":6891,"user_id":168196,"user_type":"registered"},"post_count":2,"score":395},{"user":{"reputation":452729,"user_id":69083,"user_type":"registered"},"post_count":45,"score":377},{"user":{"reputation":7102,"user_id":1515834,"user_type":"registered","accept_rate":90},"post_count":2,"score":362},{"user":{"reputation":88479,"user_id":1249581,"user_type":"registered","accept_rate":68},"post_count":27,"score":354},{"user":{"reputation":8885,"user_id":37685,"user_type":"registered","accept_rate":89},"post_count":1,"score":330},{"user":{"reputation":7477,"user_id":173347,"user_type":"registered","accept_rate":95},"post_count":2,"score":323}],"has_more":false,"quota_max":10000,"quota_remaining":9611}