{"items":[{"user":{"reputation":637053,"user_id":23354,"user_type":"moderator","accept_rate":98},"post_count":743,"score":3597},{"user":{"reputation":910370,"user_id":22656,"user_type":"registered","accept_rate":86},"post_count":146,"score":2356},{"user":{"reputation":698854,"user_id":29407,"user_type":"registered","accept_rate":91},"post_count":149,"score":1453},{"user":{"reputation":19797,"user_id":56829,"user_type":"registered","accept_rate":82},"post_count":2,"score":1137},{"user":{"reputation":357483,"user_id":57695,"user_type":"registered","accept_rate":83},"post_count":152,"score":570},{"user":{"reputation":39983,"user_id":10263,"user_type":"registered","accept_rate":100},"post_count":136,"score":556},{"user":{"reputation":115470,"user_id":20654,"user_type":"registered","accept_rate":81},"post_count":11,"score":486},{"user":{"reputation":82993,"user_id":8815,"user_type":"registered","accept_rate":85},"post_count":8,"score":484},{"user":{"reputation":60262,"user_id":59501,"user_type":"registered","accept_rate":75},"post_count":132,"score":476},{"user":{"reputation":281262,"user_id":21234,"user_type":"registered","accept_rate":91},"post_count":22,"score":465},{"user":{"reputation":4504,"user_id":611062,"user_type":"registered"},"post_count":1,"score":437},{"user":{"reputation":130784,"user_id":24874,"user_type":"registered","accept_rate":79},"post_count":7,"score":436},{"user":{"reputation":17469,"user_id":5469,"user_type":"registered","accept_rate":94},"post_count":1,"score":424},{"user":{"reputation":139370,"user_id":76217,"user_type":"registered","accept_rate":96},"post_count":5,"score":383},{"user":{"reputation":3917,"user_id":738764,"user_type":"registered","accept_rate":0},"post_count":1,"score":371},{"user":{"reputation":6988,"user_id":884474,"user_type":"registered","accept_rate":88},"post_count":1,"score":370},{"user":{"reputation":201034,"user_id":207421,"user_type":"registered","accept_rate":82},"post_count":387,"score":344},{"user":{"reputation":17302,"user_id":8026,"user_type":"registered","accept_rate":63},"post_count":2,"score":343},{"user":{"reputation":6018,"user_id":3566,"user_type":"registered","accept_rate":50},"post_count":1,"score":335},{"user":{"reputation":3378,"user_id":360863,"user_type":"registered"},"post_count":1,"score":331}],"has_more":false,"quota_max":10000,"quota_remaining":9698}