{"items":[{"user":{"reputation":82157,"user_id":171456,"user_type":"registered","accept_rate":100},"post_count":1024,"score":5965},{"user":{"reputation":59211,"user_id":680398,"user_type":"registered"},"post_count":200,"score":4053},{"user":{"reputation":39261,"user_id":1366033,"user_type":"registered","accept_rate":88},"post_count":218,"score":2283},{"user":{"reputation":42749,"user_id":1238019,"user_type":"registered","accept_rate":88},"post_count":107,"score":2126},{"user":{"reputation":36335,"user_id":1596547,"user_type":"registered","accept_rate":83},"post_count":378,"score":1935},{"user":{"reputation":35025,"user_id":2049063,"user_type":"registered"},"post_count":104,"score":1828},{"user":{"reputation":20794,"user_id":570918,"user_type":"registered","accept_rate":93},"post_count":124,"score":1390},{"user":{"reputation":26369,"user_id":681807,"user_type":"registered","accept_rate":100},"post_count":11,"score":1211},{"user":{"reputation":14418,"user_id":1478467,"user_type":"registered"},"post_count":159,"score":1172},{"user":{"reputation":12456,"user_id":1578667,"user_type":"registered","accept_rate":82},"post_count":84,"score":1078},{"user":{"reputation":50253,"user_id":1725764,"user_type":"registered"},"post_count":42,"score":1046},{"user":{"reputation":18561,"user_id":1004312,"user_type":"registered","accept_rate":86},"post_count":223,"score":1023},{"user":{"reputation":73004,"user_id":1317805,"user_type":"registered","accept_rate":90},"post_count":65,"score":900},{"user":{"reputation":16308,"user_id":1751766,"user_type":"registered"},"post_count":262,"score":887},{"user":{"reputation":16269,"user_id":1069899,"user_type":"registered","accept_rate":85},"post_count":1,"score":884},{"user":{"reputation":54834,"user_id":369707,"user_type":"registered","accept_rate":100},"post_count":37,"score":823},{"user":{"reputation":7906,"user_id":1268533,"user_type":"registered","accept_rate":80},"post_count":1,"score":780},{"user":{"reputation":9783,"user_id":341692,"user_type":"registered","accept_rate":83},"post_count":46,"score":754},{"user":{"reputation":13932,"user_id":2454790,"user_type":"registered","accept_rate":62},"post_count":256,"score":745},{"user":{"reputation":8419,"user_id":1416911,"user_type":"registered","accept_rate":100},"post_count":93,"score":694}],"has_more":false,"quota_max":300,"quota_remaining":211}