{"items":[{"user":{"reputation":56307,"user_id":1755,"user_type":"registered","accept_rate":78},"post_count":1559,"score":2693},{"user":{"reputation":14855,"user_id":424723,"user_type":"registered","accept_rate":67},"post_count":439,"score":1106},{"user":{"reputation":13372,"user_id":566791,"user_type":"registered","accept_rate":60},"post_count":401,"score":952},{"user":{"reputation":54350,"user_id":187697,"user_type":"registered","accept_rate":100},"post_count":312,"score":931},{"user":{"reputation":20936,"user_id":95309,"user_type":"registered","accept_rate":96},"post_count":459,"score":792},{"user":{"reputation":45792,"user_id":249933,"user_type":"registered","accept_rate":83},"post_count":371,"score":777},{"user":{"reputation":910370,"user_id":22656,"user_type":"registered","accept_rate":86},"post_count":204,"score":700},{"user":{"reputation":26468,"user_id":869621,"user_type":"registered"},"post_count":354,"score":638},{"user":{"reputation":13833,"user_id":303696,"user_type":"registered","accept_rate":90},"post_count":448,"score":633},{"user":{"reputation":56736,"user_id":373321,"user_type":"registered","accept_rate":76},"post_count":300,"score":577},{"user":{"reputation":145541,"user_id":17516,"user_type":"registered","accept_rate":79},"post_count":138,"score":470},{"user":{"reputation":7977,"user_id":820813,"user_type":"registered","accept_rate":40},"post_count":295,"score":464},{"user":{"reputation":55317,"user_id":3603,"user_type":"registered","accept_rate":85},"post_count":222,"score":426},{"user":{"reputation":71908,"user_id":241631,"user_type":"registered","accept_rate":90},"post_count":125,"score":415},{"user":{"reputation":7691,"user_id":90457,"user_type":"registered","accept_rate":100},"post_count":69,"score":378},{"user":{"reputation":12882,"user_id":50468,"user_type":"registered","accept_rate":70},"post_count":175,"score":319},{"user":{"reputation":5974,"user_id":358596,"user_type":"registered"},"post_count":182,"score":319},{"user":{"reputation":15113,"user_id":81687,"user_type":"registered"},"post_count":62,"score":267},{"user":{"reputation":9235,"user_id":336186,"user_type":"registered","accept_rate":71},"post_count":159,"score":227},{"user":{"reputation":8248,"user_id":694641,"user_type":"registered"},"post_count":130,"score":223}],"has_more":false,"quota_max":10000,"quota_remaining":9677}