{"items":[{"user":{"reputation":33562,"user_id":1338,"user_type":"registered","accept_rate":76},"post_count":636,"score":1068},{"user":{"reputation":56736,"user_id":373321,"user_type":"registered","accept_rate":76},"post_count":321,"score":738},{"user":{"reputation":17111,"user_id":4984832,"user_type":"registered","accept_rate":83},"post_count":599,"score":705},{"user":{"reputation":69601,"user_id":33686,"user_type":"registered","accept_rate":87},"post_count":1,"score":510},{"user":{"reputation":10810,"user_id":293609,"user_type":"registered"},"post_count":48,"score":462},{"user":{"reputation":39190,"user_id":220643,"user_type":"registered"},"post_count":162,"score":460},{"user":{"reputation":7661,"user_id":1489968,"user_type":"registered","accept_rate":67},"post_count":228,"score":416},{"user":{"reputation":17301,"user_id":183422,"user_type":"registered"},"post_count":137,"score":389},{"user":{"reputation":11132,"user_id":368379,"user_type":"registered","accept_rate":88},"post_count":211,"score":371},{"user":{"reputation":8653,"user_id":1063783,"user_type":"registered","accept_rate":77},"post_count":109,"score":352},{"user":{"reputation":3712,"user_id":494571,"user_type":"registered","accept_rate":68},"post_count":5,"score":330},{"user":{"reputation":5618,"user_id":1099111,"user_type":"registered","accept_rate":100},"post_count":111,"score":283},{"user":{"reputation":7218,"user_id":3419103,"user_type":"registered","accept_rate":84},"post_count":23,"score":250},{"user":{"reputation":5180,"user_id":1048571,"user_type":"registered","accept_rate":80},"post_count":168,"score":246},{"user":{"reputation":4181,"user_id":3148214,"user_type":"registered"},"post_count":167,"score":238},{"user":{"reputation":2187,"user_id":3085228,"user_type":"registered"},"post_count":30,"score":204},{"user":{"reputation":3434,"user_id":1107580,"user_type":"registered","accept_rate":80},"post_count":130,"score":178},{"user":{"reputation":7248,"user_id":2023316,"user_type":"registered","accept_rate":75},"post_count":53,"score":168},{"user":{"reputation":22020,"user_id":239438,"user_type":"registered","accept_rate":79},"post_count":100,"score":163},{"user":{"reputation":3432,"user_id":3849465,"user_type":"registered"},"post_count":94,"score":154}],"has_more":false,"quota_max":10000,"quota_remaining":9645}